ondewo/__init__.py
ondewo/sip/__init__.py
ondewo/sip/sip_pb2.py
ondewo/sip/sip_pb2.pyi
ondewo/sip/sip_pb2_grpc.py
ondewo/sip/client/__init__.py
ondewo/sip/client/async_client.py
ondewo/sip/client/async_services_container.py
ondewo/sip/client/client.py
ondewo/sip/client/client_config.py
ondewo/sip/client/services_container.py
ondewo/sip/client/services/__init__.py
ondewo/sip/client/services/async_sip.py
ondewo/sip/client/services/sip.py
ondewo_sip_client-5.3.0.dist-info/LICENSE
ondewo_sip_client-5.3.0.dist-info/METADATA
ondewo_sip_client-5.3.0.dist-info/WHEEL
ondewo_sip_client-5.3.0.dist-info/top_level.txt
ondewo_sip_client-5.3.0.dist-info/RECORD
